dbferry/__init__.py
dbferry/cli.py
dbferry/core/config.py
dbferry/core/connection.py
dbferry/core/console.py
dbferry/core/logger.py
dbferry/core/migrate.py
dbferry/core/schema.py
dbferry/core/verify.py
dbferry/core/adapters/base.py
dbferry/core/adapters/postgres.py
dbferry-0.1.2.dist-info/licenses/LICENSE
dbferry-0.1.2.dist-info/METADATA
dbferry-0.1.2.dist-info/WHEEL
dbferry-0.1.2.dist-info/entry_points.txt
dbferry-0.1.2.dist-info/top_level.txt
dbferry-0.1.2.dist-info/RECORD
