Metadata-Version: 2.4
Name: dbferry
Version: 0.1.2
Summary: A secure, local-first database migration tool
Author-email: Abdulalim Ladan <aaladan453@gmail.com>
License-Expression: Apache-2.0
Project-URL: Homepage, https://github.com/AbdLim/dbferry
Project-URL: Documentation, https://github.com/AbdLim/dbferry#readme
Project-URL: Repository, https://github.com/AbdLim/dbferry.git
Project-URL: Issues, https://github.com/AbdLim/dbferry/issues
Project-URL: Changelog, https://github.com/AbdLim/dbferry/releases
Requires-Python: >=3.13
License-File: LICENSE
Requires-Dist: click>=8.1.7
Requires-Dist: rich>=13.7.0
Requires-Dist: sqlalchemy>=2.0.25
Requires-Dist: fastapi>=0.115.0
Requires-Dist: uvicorn>=0.30.1
Requires-Dist: python-dotenv>=1.0.1
Requires-Dist: psycopg[binary]>=3.1.19
Requires-Dist: pymysql>=1.1.0
Requires-Dist: pyyaml>=6.0.3
Requires-Dist: psycopg2>=2.9.11
Requires-Dist: networkx>=3.5
Provides-Extra: dev
Requires-Dist: pytest; extra == "dev"
Requires-Dist: ruff; extra == "dev"
Requires-Dist: black; extra == "dev"
Requires-Dist: mypy; extra == "dev"
Dynamic: license-file
